sensorpro_ble/__init__.py
sensorpro_ble/parser.py
sensorpro_ble/py.typed
sensorpro_ble-1.0.0.dist-info/METADATA
sensorpro_ble-1.0.0.dist-info/WHEEL
sensorpro_ble-1.0.0.dist-info/licenses/LICENSE
sensorpro_ble-1.0.0.dist-info/RECORD
